{"pagelen": 50, "values": [{"update": {"description": "The main change here is to document the parsing states for the proposed pose frame semantics, highlighting the differences with the legacy behavior using italics. I've also included two small changes in 8701b60 and b213344 that change the target version of the SDF spec to 1.7 (instead of 2.0) and also refers to some links as documentation rather than tutorials.", "title": "Parsing stages for proposed pose behavior", "destination": {"commit": {"hash": "49d31c1813fc", "type": "commit", "links": {"self": {"href": "data/repositories/osrf/sdf_tutorials/commit/49d31c1813fc.json"}, "html": {"href": "#!/osrf/sdf_tutorials/commits/49d31c1813fc"}}}, "repository": {"links": {"self": {"href": "data/repositories/osrf/sdf_tutorials.json"}, "html": {"href": "#!/osrf/sdf_tutorials"}, "avatar": {"href": "data/bytebucket.org/ravatar/{c7e79ad4-567f-412c-8738-289b2cd29c59}ts=markdown"}}, "type": "repository", "name": "sdf_tutorials", "full_name": "osrf/sdf_tutorials", "uuid": "{c7e79ad4-567f-412c-8738-289b2cd29c59}"}, "branch": {"name": "default"}}, "reason": "", "source": {"commit": {"hash": "3666141612a2", "type": "commit", "links": {"self": {"href": "data/repositories/osrf/sdf_tutorials/commit/3666141612a2.json"}, "html": {"href": "#!/osrf/sdf_tutorials/commits/3666141612a2"}}}, "repository": {"links": {"self": {"href": "data/repositories/osrf/sdf_tutorials.json"}, "html": {"href": "#!/osrf/sdf_tutorials"}, "avatar": {"href": "data/bytebucket.org/ravatar/{c7e79ad4-567f-412c-8738-289b2cd29c59}ts=markdown"}}, "type": "repository", "name": "sdf_tutorials", "full_name": "osrf/sdf_tutorials", "uuid": "{c7e79ad4-567f-412c-8738-289b2cd29c59}"}, "branch": {"name": "pose_frame_parsing_proposal"}}, "state": "MERGED", "author": {"display_name": "Addisu Z. Taddese", "uuid": "{9d7fdc68-d270-4080-bf03-4df0d0dbf635}", "links": {"self": {"href": "https://api.bitbucket.org/2.0/users/%7B9d7fdc68-d270-4080-bf03-4df0d0dbf635%7D"}, "html": {"href": "https://bitbucket.org/%7B9d7fdc68-d270-4080-bf03-4df0d0dbf635%7D/"}, "avatar": {"href": "https://avatar-management--avatars.us-west-2.prod.public.atl-paas.net/557058:90bc87b0-2886-4377-a17c-3a6629a697ff/afbf9be5-1e4c-4810-89d4-e58831f34b11/128"}}, "nickname": "azeey", "type": "user", "account_id": "557058:90bc87b0-2886-4377-a17c-3a6629a697ff"}, "date": "2019-07-24T07:27:05.001709+00:00"}, "pull_request": {"type": "pullrequest", "id": 25, "links": {"self": {"href": "data/repositories/osrf/sdf_tutorials/pullrequests/25.json"}, "html": {"href": "#!/osrf/sdf_tutorials/pull-requests/25"}}, "title": "Parsing stages for proposed pose behavior"}}, {"comment": {"links": {"self": {"href": "data/repositories/osrf/sdf_tutorials/pullrequests/25/comments/110447648.json"}, "html": {"href": "#!/osrf/sdf_tutorials/pull-requests/25/_/diff#comment-110447648"}}, "parent": {"id": 109176889, "links": {"self": {"href": "data/repositories/osrf/sdf_tutorials/pullrequests/25/comments/109176889.json"}, "html": {"href": "#!/osrf/sdf_tutorials/pull-requests/25/_/diff#comment-109176889"}}}, "deleted": false, "pullrequest": {"type": "pullrequest", "id": 25, "links": {"self": {"href": "data/repositories/osrf/sdf_tutorials/pullrequests/25.json"}, "html": {"href": "#!/osrf/sdf_tutorials/pull-requests/25"}}, "title": "Parsing stages for proposed pose behavior"}, "content": {"raw": "3666141", "markup": "markdown", "html": "<p><a href=\"#!/osrf/sdf_tutorials/commits/3666141\" rel=\"nofollow\" class=\"ap-connect-link\">3666141</a></p>", "type": "rendered"}, "created_on": "2019-07-24T07:26:57.732002+00:00", "user": {"display_name": "Addisu Z. Taddese", "uuid": "{9d7fdc68-d270-4080-bf03-4df0d0dbf635}", "links": {"self": {"href": "https://api.bitbucket.org/2.0/users/%7B9d7fdc68-d270-4080-bf03-4df0d0dbf635%7D"}, "html": {"href": "https://bitbucket.org/%7B9d7fdc68-d270-4080-bf03-4df0d0dbf635%7D/"}, "avatar": {"href": "https://avatar-management--avatars.us-west-2.prod.public.atl-paas.net/557058:90bc87b0-2886-4377-a17c-3a6629a697ff/afbf9be5-1e4c-4810-89d4-e58831f34b11/128"}}, "nickname": "azeey", "type": "user", "account_id": "557058:90bc87b0-2886-4377-a17c-3a6629a697ff"}, "inline": {}, "updated_on": "2019-07-24T07:26:57.747884+00:00", "type": "pullrequest_comment", "id": 110447648}, "pull_request": {"type": "pullrequest", "id": 25, "links": {"self": {"href": "data/repositories/osrf/sdf_tutorials/pullrequests/25.json"}, "html": {"href": "#!/osrf/sdf_tutorials/pull-requests/25"}}, "title": "Parsing stages for proposed pose behavior"}}, {"update": {"description": "The main change here is to document the parsing states for the proposed pose frame semantics, highlighting the differences with the legacy behavior using italics. I've also included two small changes in 8701b60 and b213344 that change the target version of the SDF spec to 1.7 (instead of 2.0) and also refers to some links as documentation rather than tutorials.", "title": "Parsing stages for proposed pose behavior", "destination": {"commit": {"hash": "49d31c1813fc", "type": "commit", "links": {"self": {"href": "data/repositories/osrf/sdf_tutorials/commit/49d31c1813fc.json"}, "html": {"href": "#!/osrf/sdf_tutorials/commits/49d31c1813fc"}}}, "repository": {"links": {"self": {"href": "data/repositories/osrf/sdf_tutorials.json"}, "html": {"href": "#!/osrf/sdf_tutorials"}, "avatar": {"href": "data/bytebucket.org/ravatar/{c7e79ad4-567f-412c-8738-289b2cd29c59}ts=markdown"}}, "type": "repository", "name": "sdf_tutorials", "full_name": "osrf/sdf_tutorials", "uuid": "{c7e79ad4-567f-412c-8738-289b2cd29c59}"}, "branch": {"name": "default"}}, "reason": "", "source": {"commit": {"hash": "3666141612a2", "type": "commit", "links": {"self": {"href": "data/repositories/osrf/sdf_tutorials/commit/3666141612a2.json"}, "html": {"href": "#!/osrf/sdf_tutorials/commits/3666141612a2"}}}, "repository": {"links": {"self": {"href": "data/repositories/osrf/sdf_tutorials.json"}, "html": {"href": "#!/osrf/sdf_tutorials"}, "avatar": {"href": "data/bytebucket.org/ravatar/{c7e79ad4-567f-412c-8738-289b2cd29c59}ts=markdown"}}, "type": "repository", "name": "sdf_tutorials", "full_name": "osrf/sdf_tutorials", "uuid": "{c7e79ad4-567f-412c-8738-289b2cd29c59}"}, "branch": {"name": "pose_frame_parsing_proposal"}}, "state": "OPEN", "author": {"display_name": "Addisu Z. Taddese", "uuid": "{9d7fdc68-d270-4080-bf03-4df0d0dbf635}", "links": {"self": {"href": "https://api.bitbucket.org/2.0/users/%7B9d7fdc68-d270-4080-bf03-4df0d0dbf635%7D"}, "html": {"href": "https://bitbucket.org/%7B9d7fdc68-d270-4080-bf03-4df0d0dbf635%7D/"}, "avatar": {"href": "https://avatar-management--avatars.us-west-2.prod.public.atl-paas.net/557058:90bc87b0-2886-4377-a17c-3a6629a697ff/afbf9be5-1e4c-4810-89d4-e58831f34b11/128"}}, "nickname": "azeey", "type": "user", "account_id": "557058:90bc87b0-2886-4377-a17c-3a6629a697ff"}, "date": "2019-07-24T07:26:45.326440+00:00"}, "pull_request": {"type": "pullrequest", "id": 25, "links": {"self": {"href": "data/repositories/osrf/sdf_tutorials/pullrequests/25.json"}, "html": {"href": "#!/osrf/sdf_tutorials/pull-requests/25"}}, "title": "Parsing stages for proposed pose behavior"}}, {"comment": {"links": {"self": {"href": "data/repositories/osrf/sdf_tutorials/pullrequests/25/comments/109179864.json"}, "html": {"href": "#!/osrf/sdf_tutorials/pull-requests/25/_/diff#comment-109179864"}}, "parent": {"id": 109176961, "links": {"self": {"href": "data/repositories/osrf/sdf_tutorials/pullrequests/25/comments/109176961.json"}, "html": {"href": "#!/osrf/sdf_tutorials/pull-requests/25/_/diff#comment-109176961"}}}, "deleted": false, "pullrequest": {"type": "pullrequest", "id": 25, "links": {"self": {"href": "data/repositories/osrf/sdf_tutorials/pullrequests/25.json"}, "html": {"href": "#!/osrf/sdf_tutorials/pull-requests/25"}}, "title": "Parsing stages for proposed pose behavior"}, "content": {"raw": "it didn't arise from discussion. I was erring on the side of being overly verbose to be extra clear and make it easier to translate to code, but go ahead and remove it before merging if it's distracting", "markup": "markdown", "html": "<p>it didn't arise from discussion. I was erring on the side of being overly verbose to be extra clear and make it easier to translate to code, but go ahead and remove it before merging if it's distracting</p>", "type": "rendered"}, "created_on": "2019-07-13T08:54:16.473970+00:00", "user": {"display_name": "Steve Peters", "uuid": "{2ccfed09-18b8-4921-8d58-15ef01092802}", "links": {"self": {"href": "https://api.bitbucket.org/2.0/users/%7B2ccfed09-18b8-4921-8d58-15ef01092802%7D"}, "html": {"href": "https://bitbucket.org/%7B2ccfed09-18b8-4921-8d58-15ef01092802%7D/"}, "avatar": {"href": "data/secure.gravatar.com/avatar/1fb4816dad9e68337d3096f750951f6cd=httpsavatar-management--avatars.us-west-2.prod.public.atl-paas.netinitialsSP-1.png"}}, "nickname": "Steven Peters", "type": "user", "account_id": "557058:5de38267-b118-494c-aa76-4fab35448816"}, "inline": {}, "updated_on": "2019-07-13T08:54:16.483777+00:00", "type": "pullrequest_comment", "id": 109179864}, "pull_request": {"type": "pullrequest", "id": 25, "links": {"self": {"href": "data/repositories/osrf/sdf_tutorials/pullrequests/25.json"}, "html": {"href": "#!/osrf/sdf_tutorials/pull-requests/25"}}, "title": "Parsing stages for proposed pose behavior"}}, {"approval": {"date": "2019-07-13T01:38:50.456688+00:00", "pullrequest": {"type": "pullrequest", "id": 25, "links": {"self": {"href": "data/repositories/osrf/sdf_tutorials/pullrequests/25.json"}, "html": {"href": "#!/osrf/sdf_tutorials/pull-requests/25"}}, "title": "Parsing stages for proposed pose behavior"}, "user": {"display_name": "Eric Cousineau", "uuid": "{71c9fc05-02c8-45e1-adfa-13c8ac3399dc}", "links": {"self": {"href": "https://api.bitbucket.org/2.0/users/%7B71c9fc05-02c8-45e1-adfa-13c8ac3399dc%7D"}, "html": {"href": "https://bitbucket.org/%7B71c9fc05-02c8-45e1-adfa-13c8ac3399dc%7D/"}, "avatar": {"href": "https://avatar-management--avatars.us-west-2.prod.public.atl-paas.net/557057:f3a199b9-5784-4964-9644-6ef224bc7dc1/28a4d748-0fd4-4038-bf3d-55a77eb73ede/128"}}, "nickname": "eacousineau", "type": "user", "account_id": "557057:f3a199b9-5784-4964-9644-6ef224bc7dc1"}}, "pull_request": {"type": "pullrequest", "id": 25, "links": {"self": {"href": "data/repositories/osrf/sdf_tutorials/pullrequests/25.json"}, "html": {"href": "#!/osrf/sdf_tutorials/pull-requests/25"}}, "title": "Parsing stages for proposed pose behavior"}}, {"comment": {"links": {"self": {"href": "data/repositories/osrf/sdf_tutorials/pullrequests/25/comments/109176961.json"}, "html": {"href": "#!/osrf/sdf_tutorials/pull-requests/25/_/diff#comment-109176961"}}, "deleted": false, "pullrequest": {"type": "pullrequest", "id": 25, "links": {"self": {"href": "data/repositories/osrf/sdf_tutorials/pullrequests/25.json"}, "html": {"href": "#!/osrf/sdf_tutorials/pull-requests/25"}}, "title": "Parsing stages for proposed pose behavior"}, "content": {"raw": "BTW I'd be fine with the `(ie. ...)`were removed. \\(Though I\u2019m not sure if this came about from discussion.\\)", "markup": "markdown", "html": "<p>BTW I'd be fine with the <code>(ie. ...)</code>were removed. (Though I\u2019m not sure if this came about from discussion.)</p>", "type": "rendered"}, "created_on": "2019-07-13T01:36:25.743141+00:00", "user": {"display_name": "Eric Cousineau", "uuid": "{71c9fc05-02c8-45e1-adfa-13c8ac3399dc}", "links": {"self": {"href": "https://api.bitbucket.org/2.0/users/%7B71c9fc05-02c8-45e1-adfa-13c8ac3399dc%7D"}, "html": {"href": "https://bitbucket.org/%7B71c9fc05-02c8-45e1-adfa-13c8ac3399dc%7D/"}, "avatar": {"href": "https://avatar-management--avatars.us-west-2.prod.public.atl-paas.net/557057:f3a199b9-5784-4964-9644-6ef224bc7dc1/28a4d748-0fd4-4038-bf3d-55a77eb73ede/128"}}, "nickname": "eacousineau", "type": "user", "account_id": "557057:f3a199b9-5784-4964-9644-6ef224bc7dc1"}, "inline": {}, "updated_on": "2019-07-13T01:36:32.572740+00:00", "type": "pullrequest_comment", "id": 109176961}, "pull_request": {"type": "pullrequest", "id": 25, "links": {"self": {"href": "data/repositories/osrf/sdf_tutorials/pullrequests/25.json"}, "html": {"href": "#!/osrf/sdf_tutorials/pull-requests/25"}}, "title": "Parsing stages for proposed pose behavior"}}, {"comment": {"links": {"self": {"href": "data/repositories/osrf/sdf_tutorials/pullrequests/25/comments/109176889.json"}, "html": {"href": "#!/osrf/sdf_tutorials/pull-requests/25/_/diff#comment-109176889"}}, "deleted": false, "pullrequest": {"type": "pullrequest", "id": 25, "links": {"self": {"href": "data/repositories/osrf/sdf_tutorials/pullrequests/25.json"}, "html": {"href": "#!/osrf/sdf_tutorials/pull-requests/25"}}, "title": "Parsing stages for proposed pose behavior"}, "content": {"raw": "nit Can we fully specify \u201cSDFormat 1.7\u201d, rather than \u201csdf 1.7\u201d?", "markup": "markdown", "html": "<p>nit Can we fully specify \u201cSDFormat 1.7\u201d, rather than \u201csdf 1.7\u201d?</p>", "type": "rendered"}, "created_on": "2019-07-13T01:29:05.365393+00:00", "user": {"display_name": "Eric Cousineau", "uuid": "{71c9fc05-02c8-45e1-adfa-13c8ac3399dc}", "links": {"self": {"href": "https://api.bitbucket.org/2.0/users/%7B71c9fc05-02c8-45e1-adfa-13c8ac3399dc%7D"}, "html": {"href": "https://bitbucket.org/%7B71c9fc05-02c8-45e1-adfa-13c8ac3399dc%7D/"}, "avatar": {"href": "https://avatar-management--avatars.us-west-2.prod.public.atl-paas.net/557057:f3a199b9-5784-4964-9644-6ef224bc7dc1/28a4d748-0fd4-4038-bf3d-55a77eb73ede/128"}}, "nickname": "eacousineau", "type": "user", "account_id": "557057:f3a199b9-5784-4964-9644-6ef224bc7dc1"}, "inline": {}, "updated_on": "2019-07-13T01:29:05.372531+00:00", "type": "pullrequest_comment", "id": 109176889}, "pull_request": {"type": "pullrequest", "id": 25, "links": {"self": {"href": "data/repositories/osrf/sdf_tutorials/pullrequests/25.json"}, "html": {"href": "#!/osrf/sdf_tutorials/pull-requests/25"}}, "title": "Parsing stages for proposed pose behavior"}}, {"approval": {"date": "2019-07-12T16:33:10.349976+00:00", "pullrequest": {"type": "pullrequest", "id": 25, "links": {"self": {"href": "data/repositories/osrf/sdf_tutorials/pullrequests/25.json"}, "html": {"href": "#!/osrf/sdf_tutorials/pull-requests/25"}}, "title": "Parsing stages for proposed pose behavior"}, "user": {"display_name": "Addisu Z. Taddese", "uuid": "{9d7fdc68-d270-4080-bf03-4df0d0dbf635}", "links": {"self": {"href": "https://api.bitbucket.org/2.0/users/%7B9d7fdc68-d270-4080-bf03-4df0d0dbf635%7D"}, "html": {"href": "https://bitbucket.org/%7B9d7fdc68-d270-4080-bf03-4df0d0dbf635%7D/"}, "avatar": {"href": "https://avatar-management--avatars.us-west-2.prod.public.atl-paas.net/557058:90bc87b0-2886-4377-a17c-3a6629a697ff/afbf9be5-1e4c-4810-89d4-e58831f34b11/128"}}, "nickname": "azeey", "type": "user", "account_id": "557058:90bc87b0-2886-4377-a17c-3a6629a697ff"}}, "pull_request": {"type": "pullrequest", "id": 25, "links": {"self": {"href": "data/repositories/osrf/sdf_tutorials/pullrequests/25.json"}, "html": {"href": "#!/osrf/sdf_tutorials/pull-requests/25"}}, "title": "Parsing stages for proposed pose behavior"}}, {"update": {"description": "The main change here is to document the parsing states for the proposed pose frame semantics, highlighting the differences with the legacy behavior using italics. I've also included two small changes in 8701b60 and b213344 that change the target version of the SDF spec to 1.7 (instead of 2.0) and also refers to some links as documentation rather than tutorials.", "title": "Parsing stages for proposed pose behavior", "destination": {"commit": {"hash": "ab5380111d65", "type": "commit", "links": {"self": {"href": "data/repositories/osrf/sdf_tutorials/commit/ab5380111d65.json"}, "html": {"href": "#!/osrf/sdf_tutorials/commits/ab5380111d65"}}}, "repository": {"links": {"self": {"href": "data/repositories/osrf/sdf_tutorials.json"}, "html": {"href": "#!/osrf/sdf_tutorials"}, "avatar": {"href": "data/bytebucket.org/ravatar/{c7e79ad4-567f-412c-8738-289b2cd29c59}ts=markdown"}}, "type": "repository", "name": "sdf_tutorials", "full_name": "osrf/sdf_tutorials", "uuid": "{c7e79ad4-567f-412c-8738-289b2cd29c59}"}, "branch": {"name": "default"}}, "reason": "", "source": {"commit": {"hash": "385148740d21", "type": "commit", "links": {"self": {"href": "data/repositories/osrf/sdf_tutorials/commit/385148740d21.json"}, "html": {"href": "#!/osrf/sdf_tutorials/commits/385148740d21"}}}, "repository": {"links": {"self": {"href": "data/repositories/osrf/sdf_tutorials.json"}, "html": {"href": "#!/osrf/sdf_tutorials"}, "avatar": {"href": "data/bytebucket.org/ravatar/{c7e79ad4-567f-412c-8738-289b2cd29c59}ts=markdown"}}, "type": "repository", "name": "sdf_tutorials", "full_name": "osrf/sdf_tutorials", "uuid": "{c7e79ad4-567f-412c-8738-289b2cd29c59}"}, "branch": {"name": "pose_frame_parsing_proposal"}}, "state": "OPEN", "author": {"display_name": "Steve Peters", "uuid": "{2ccfed09-18b8-4921-8d58-15ef01092802}", "links": {"self": {"href": "https://api.bitbucket.org/2.0/users/%7B2ccfed09-18b8-4921-8d58-15ef01092802%7D"}, "html": {"href": "https://bitbucket.org/%7B2ccfed09-18b8-4921-8d58-15ef01092802%7D/"}, "avatar": {"href": "data/secure.gravatar.com/avatar/1fb4816dad9e68337d3096f750951f6cd=httpsavatar-management--avatars.us-west-2.prod.public.atl-paas.netinitialsSP-1.png"}}, "nickname": "Steven Peters", "type": "user", "account_id": "557058:5de38267-b118-494c-aa76-4fab35448816"}, "date": "2019-07-11T22:08:03.347701+00:00"}, "pull_request": {"type": "pullrequest", "id": 25, "links": {"self": {"href": "data/repositories/osrf/sdf_tutorials/pullrequests/25.json"}, "html": {"href": "#!/osrf/sdf_tutorials/pull-requests/25"}}, "title": "Parsing stages for proposed pose behavior"}}, {"comment": {"links": {"self": {"href": "data/repositories/osrf/sdf_tutorials/pullrequests/25/comments/109022326.json"}, "html": {"href": "#!/osrf/sdf_tutorials/pull-requests/25/_/diff#comment-109022326"}}, "parent": {"id": 109022273, "links": {"self": {"href": "data/repositories/osrf/sdf_tutorials/pullrequests/25/comments/109022273.json"}, "html": {"href": "#!/osrf/sdf_tutorials/pull-requests/25/_/diff#comment-109022273"}}}, "deleted": false, "pullrequest": {"type": "pullrequest", "id": 25, "links": {"self": {"href": "data/repositories/osrf/sdf_tutorials/pullrequests/25.json"}, "html": {"href": "#!/osrf/sdf_tutorials/pull-requests/25"}}, "title": "Parsing stages for proposed pose behavior"}, "content": {"raw": "321e29027d2f", "markup": "markdown", "html": "<p><a href=\"#!/osrf/sdf_tutorials/commits/321e29027d2f\" rel=\"nofollow\" class=\"ap-connect-link\">321e29027d2f</a></p>", "type": "rendered"}, "created_on": "2019-07-11T22:07:32.916446+00:00", "user": {"display_name": "Steve Peters", "uuid": "{2ccfed09-18b8-4921-8d58-15ef01092802}", "links": {"self": {"href": "https://api.bitbucket.org/2.0/users/%7B2ccfed09-18b8-4921-8d58-15ef01092802%7D"}, "html": {"href": "https://bitbucket.org/%7B2ccfed09-18b8-4921-8d58-15ef01092802%7D/"}, "avatar": {"href": "data/secure.gravatar.com/avatar/1fb4816dad9e68337d3096f750951f6cd=httpsavatar-management--avatars.us-west-2.prod.public.atl-paas.netinitialsSP-1.png"}}, "nickname": "Steven Peters", "type": "user", "account_id": "557058:5de38267-b118-494c-aa76-4fab35448816"}, "inline": {}, "updated_on": "2019-07-11T22:07:32.927384+00:00", "type": "pullrequest_comment", "id": 109022326}, "pull_request": {"type": "pullrequest", "id": 25, "links": {"self": {"href": "data/repositories/osrf/sdf_tutorials/pullrequests/25.json"}, "html": {"href": "#!/osrf/sdf_tutorials/pull-requests/25"}}, "title": "Parsing stages for proposed pose behavior"}}, {"update": {"description": "The main change here is to document the parsing states for the proposed pose frame semantics, highlighting the differences with the legacy behavior using italics. I've also included two small changes in 8701b60 and b213344 that change the target version of the SDF spec to 1.7 (instead of 2.0) and also refers to some links as documentation rather than tutorials.", "title": "Parsing stages for proposed pose behavior", "destination": {"commit": {"hash": "ab5380111d65", "type": "commit", "links": {"self": {"href": "data/repositories/osrf/sdf_tutorials/commit/ab5380111d65.json"}, "html": {"href": "#!/osrf/sdf_tutorials/commits/ab5380111d65"}}}, "repository": {"links": {"self": {"href": "data/repositories/osrf/sdf_tutorials.json"}, "html": {"href": "#!/osrf/sdf_tutorials"}, "avatar": {"href": "data/bytebucket.org/ravatar/{c7e79ad4-567f-412c-8738-289b2cd29c59}ts=markdown"}}, "type": "repository", "name": "sdf_tutorials", "full_name": "osrf/sdf_tutorials", "uuid": "{c7e79ad4-567f-412c-8738-289b2cd29c59}"}, "branch": {"name": "default"}}, "reason": "", "source": {"commit": {"hash": "321e29027d2f", "type": "commit", "links": {"self": {"href": "data/repositories/osrf/sdf_tutorials/commit/321e29027d2f.json"}, "html": {"href": "#!/osrf/sdf_tutorials/commits/321e29027d2f"}}}, "repository": {"links": {"self": {"href": "data/repositories/osrf/sdf_tutorials.json"}, "html": {"href": "#!/osrf/sdf_tutorials"}, "avatar": {"href": "data/bytebucket.org/ravatar/{c7e79ad4-567f-412c-8738-289b2cd29c59}ts=markdown"}}, "type": "repository", "name": "sdf_tutorials", "full_name": "osrf/sdf_tutorials", "uuid": "{c7e79ad4-567f-412c-8738-289b2cd29c59}"}, "branch": {"name": "pose_frame_parsing_proposal"}}, "state": "OPEN", "author": {"display_name": "Steve Peters", "uuid": "{2ccfed09-18b8-4921-8d58-15ef01092802}", "links": {"self": {"href": "https://api.bitbucket.org/2.0/users/%7B2ccfed09-18b8-4921-8d58-15ef01092802%7D"}, "html": {"href": "https://bitbucket.org/%7B2ccfed09-18b8-4921-8d58-15ef01092802%7D/"}, "avatar": {"href": "data/secure.gravatar.com/avatar/1fb4816dad9e68337d3096f750951f6cd=httpsavatar-management--avatars.us-west-2.prod.public.atl-paas.netinitialsSP-1.png"}}, "nickname": "Steven Peters", "type": "user", "account_id": "557058:5de38267-b118-494c-aa76-4fab35448816"}, "date": "2019-07-11T22:07:25.836048+00:00"}, "pull_request": {"type": "pullrequest", "id": 25, "links": {"self": {"href": "data/repositories/osrf/sdf_tutorials/pullrequests/25.json"}, "html": {"href": "#!/osrf/sdf_tutorials/pull-requests/25"}}, "title": "Parsing stages for proposed pose behavior"}}, {"comment": {"links": {"self": {"href": "data/repositories/osrf/sdf_tutorials/pullrequests/25/comments/109022273.json"}, "html": {"href": "#!/osrf/sdf_tutorials/pull-requests/25/_/diff#comment-109022273"}}, "parent": {"id": 108991959, "links": {"self": {"href": "data/repositories/osrf/sdf_tutorials/pullrequests/25/comments/108991959.json"}, "html": {"href": "#!/osrf/sdf_tutorials/pull-requests/25/_/diff#comment-108991959"}}}, "deleted": false, "pullrequest": {"type": "pullrequest", "id": 25, "links": {"self": {"href": "data/repositories/osrf/sdf_tutorials/pullrequests/25.json"}, "html": {"href": "#!/osrf/sdf_tutorials/pull-requests/25"}}, "title": "Parsing stages for proposed pose behavior"}, "content": {"raw": "I meant to say only the Title is italicized; I'll fix it", "markup": "markdown", "html": "<p>I meant to say only the Title is italicized; I'll fix it</p>", "type": "rendered"}, "created_on": "2019-07-11T22:06:33.607914+00:00", "user": {"display_name": "Steve Peters", "uuid": "{2ccfed09-18b8-4921-8d58-15ef01092802}", "links": {"self": {"href": "https://api.bitbucket.org/2.0/users/%7B2ccfed09-18b8-4921-8d58-15ef01092802%7D"}, "html": {"href": "https://bitbucket.org/%7B2ccfed09-18b8-4921-8d58-15ef01092802%7D/"}, "avatar": {"href": "data/secure.gravatar.com/avatar/1fb4816dad9e68337d3096f750951f6cd=httpsavatar-management--avatars.us-west-2.prod.public.atl-paas.netinitialsSP-1.png"}}, "nickname": "Steven Peters", "type": "user", "account_id": "557058:5de38267-b118-494c-aa76-4fab35448816"}, "inline": {}, "updated_on": "2019-07-11T22:06:33.617808+00:00", "type": "pullrequest_comment", "id": 109022273}, "pull_request": {"type": "pullrequest", "id": 25, "links": {"self": {"href": "data/repositories/osrf/sdf_tutorials/pullrequests/25.json"}, "html": {"href": "#!/osrf/sdf_tutorials/pull-requests/25"}}, "title": "Parsing stages for proposed pose behavior"}}, {"comment": {"links": {"self": {"href": "data/repositories/osrf/sdf_tutorials/pullrequests/25/comments/108991959.json"}, "html": {"href": "#!/osrf/sdf_tutorials/pull-requests/25/_/diff#comment-108991959"}}, "deleted": false, "pullrequest": {"type": "pullrequest", "id": 25, "links": {"self": {"href": "data/repositories/osrf/sdf_tutorials/pullrequests/25.json"}, "html": {"href": "#!/osrf/sdf_tutorials/pull-requests/25"}}, "title": "Parsing stages for proposed pose behavior"}, "content": {"raw": "What's the highlight supposed to do? I only see the titles in bold face with italics.", "markup": "markdown", "html": "<p>What's the highlight supposed to do? I only see the titles in bold face with italics.</p>", "type": "rendered"}, "created_on": "2019-07-11T17:14:56.920484+00:00", "user": {"display_name": "Addisu Z. Taddese", "uuid": "{9d7fdc68-d270-4080-bf03-4df0d0dbf635}", "links": {"self": {"href": "https://api.bitbucket.org/2.0/users/%7B9d7fdc68-d270-4080-bf03-4df0d0dbf635%7D"}, "html": {"href": "https://bitbucket.org/%7B9d7fdc68-d270-4080-bf03-4df0d0dbf635%7D/"}, "avatar": {"href": "https://avatar-management--avatars.us-west-2.prod.public.atl-paas.net/557058:90bc87b0-2886-4377-a17c-3a6629a697ff/afbf9be5-1e4c-4810-89d4-e58831f34b11/128"}}, "nickname": "azeey", "type": "user", "account_id": "557058:90bc87b0-2886-4377-a17c-3a6629a697ff"}, "inline": {}, "updated_on": "2019-07-11T17:14:56.931657+00:00", "type": "pullrequest_comment", "id": 108991959}, "pull_request": {"type": "pullrequest", "id": 25, "links": {"self": {"href": "data/repositories/osrf/sdf_tutorials/pullrequests/25.json"}, "html": {"href": "#!/osrf/sdf_tutorials/pull-requests/25"}}, "title": "Parsing stages for proposed pose behavior"}}, {"update": {"description": "The main change here is to document the parsing states for the proposed pose frame semantics, highlighting the differences with the legacy behavior using italics. I've also included two small changes in 8701b60 and b213344 that change the target version of the SDF spec to 1.7 (instead of 2.0) and also refers to some links as documentation rather than tutorials.", "title": "Parsing stages for proposed pose behavior", "destination": {"commit": {"hash": "ae80c771cc2a", "type": "commit", "links": {"self": {"href": "data/repositories/osrf/sdf_tutorials/commit/ae80c771cc2a.json"}, "html": {"href": "#!/osrf/sdf_tutorials/commits/ae80c771cc2a"}}}, "repository": {"links": {"self": {"href": "data/repositories/osrf/sdf_tutorials.json"}, "html": {"href": "#!/osrf/sdf_tutorials"}, "avatar": {"href": "data/bytebucket.org/ravatar/{c7e79ad4-567f-412c-8738-289b2cd29c59}ts=markdown"}}, "type": "repository", "name": "sdf_tutorials", "full_name": "osrf/sdf_tutorials", "uuid": "{c7e79ad4-567f-412c-8738-289b2cd29c59}"}, "branch": {"name": "default"}}, "reason": "", "source": {"commit": {"hash": "4fea5ed16352", "type": "commit", "links": {"self": {"href": "data/repositories/osrf/sdf_tutorials/commit/4fea5ed16352.json"}, "html": {"href": "#!/osrf/sdf_tutorials/commits/4fea5ed16352"}}}, "repository": {"links": {"self": {"href": "data/repositories/osrf/sdf_tutorials.json"}, "html": {"href": "#!/osrf/sdf_tutorials"}, "avatar": {"href": "data/bytebucket.org/ravatar/{c7e79ad4-567f-412c-8738-289b2cd29c59}ts=markdown"}}, "type": "repository", "name": "sdf_tutorials", "full_name": "osrf/sdf_tutorials", "uuid": "{c7e79ad4-567f-412c-8738-289b2cd29c59}"}, "branch": {"name": "pose_frame_parsing_proposal"}}, "state": "OPEN", "author": {"display_name": "Steve Peters", "uuid": "{2ccfed09-18b8-4921-8d58-15ef01092802}", "links": {"self": {"href": "https://api.bitbucket.org/2.0/users/%7B2ccfed09-18b8-4921-8d58-15ef01092802%7D"}, "html": {"href": "https://bitbucket.org/%7B2ccfed09-18b8-4921-8d58-15ef01092802%7D/"}, "avatar": {"href": "data/secure.gravatar.com/avatar/1fb4816dad9e68337d3096f750951f6cd=httpsavatar-management--avatars.us-west-2.prod.public.atl-paas.netinitialsSP-1.png"}}, "nickname": "Steven Peters", "type": "user", "account_id": "557058:5de38267-b118-494c-aa76-4fab35448816"}, "date": "2019-07-09T19:46:51.385722+00:00"}, "pull_request": {"type": "pullrequest", "id": 25, "links": {"self": {"href": "data/repositories/osrf/sdf_tutorials/pullrequests/25.json"}, "html": {"href": "#!/osrf/sdf_tutorials/pull-requests/25"}}, "title": "Parsing stages for proposed pose behavior"}}, {"update": {"description": "The main change here is to document the parsing states for the proposed pose frame semantics, highlighting the differences with the legacy behavior using italics. I've also included two small changes in 8701b60 and b213344 that change the target version of the SDF spec to 1.7 (instead of 2.0) and also refers to some links as documentation rather than tutorials.", "title": "Parsing stages for proposed pose behavior", "destination": {"commit": {"hash": "319d63cfb4e8", "type": "commit", "links": {"self": {"href": "data/repositories/osrf/sdf_tutorials/commit/319d63cfb4e8.json"}, "html": {"href": "#!/osrf/sdf_tutorials/commits/319d63cfb4e8"}}}, "repository": {"links": {"self": {"href": "data/repositories/osrf/sdf_tutorials.json"}, "html": {"href": "#!/osrf/sdf_tutorials"}, "avatar": {"href": "data/bytebucket.org/ravatar/{c7e79ad4-567f-412c-8738-289b2cd29c59}ts=markdown"}}, "type": "repository", "name": "sdf_tutorials", "full_name": "osrf/sdf_tutorials", "uuid": "{c7e79ad4-567f-412c-8738-289b2cd29c59}"}, "branch": {"name": "default"}}, "reason": "", "source": {"commit": {"hash": "e86fc8b9e8ad", "type": "commit", "links": {"self": {"href": "data/repositories/osrf/sdf_tutorials/commit/e86fc8b9e8ad.json"}, "html": {"href": "#!/osrf/sdf_tutorials/commits/e86fc8b9e8ad"}}}, "repository": {"links": {"self": {"href": "data/repositories/osrf/sdf_tutorials.json"}, "html": {"href": "#!/osrf/sdf_tutorials"}, "avatar": {"href": "data/bytebucket.org/ravatar/{c7e79ad4-567f-412c-8738-289b2cd29c59}ts=markdown"}}, "type": "repository", "name": "sdf_tutorials", "full_name": "osrf/sdf_tutorials", "uuid": "{c7e79ad4-567f-412c-8738-289b2cd29c59}"}, "branch": {"name": "pose_frame_parsing_proposal"}}, "state": "OPEN", "author": {"display_name": "Steve Peters", "uuid": "{2ccfed09-18b8-4921-8d58-15ef01092802}", "links": {"self": {"href": "https://api.bitbucket.org/2.0/users/%7B2ccfed09-18b8-4921-8d58-15ef01092802%7D"}, "html": {"href": "https://bitbucket.org/%7B2ccfed09-18b8-4921-8d58-15ef01092802%7D/"}, "avatar": {"href": "data/secure.gravatar.com/avatar/1fb4816dad9e68337d3096f750951f6cd=httpsavatar-management--avatars.us-west-2.prod.public.atl-paas.netinitialsSP-1.png"}}, "nickname": "Steven Peters", "type": "user", "account_id": "557058:5de38267-b118-494c-aa76-4fab35448816"}, "date": "2019-07-09T00:02:14.104038+00:00"}, "pull_request": {"type": "pullrequest", "id": 25, "links": {"self": {"href": "data/repositories/osrf/sdf_tutorials/pullrequests/25.json"}, "html": {"href": "#!/osrf/sdf_tutorials/pull-requests/25"}}, "title": "Parsing stages for proposed pose behavior"}}, {"update": {"description": "The main change here is to document the parsing states for the proposed pose frame semantics, highlighting the differences with the legacy behavior using italics. I've also included two small changes in 8701b60 and b213344 that change the target version of the SDF spec to 1.7 (instead of 2.0) and also refers to some links as documentation rather than tutorials.", "title": "Parsing stages for proposed pose behavior", "destination": {"commit": {"hash": "319d63cfb4e8", "type": "commit", "links": {"self": {"href": "data/repositories/osrf/sdf_tutorials/commit/319d63cfb4e8.json"}, "html": {"href": "#!/osrf/sdf_tutorials/commits/319d63cfb4e8"}}}, "repository": {"links": {"self": {"href": "data/repositories/osrf/sdf_tutorials.json"}, "html": {"href": "#!/osrf/sdf_tutorials"}, "avatar": {"href": "data/bytebucket.org/ravatar/{c7e79ad4-567f-412c-8738-289b2cd29c59}ts=markdown"}}, "type": "repository", "name": "sdf_tutorials", "full_name": "osrf/sdf_tutorials", "uuid": "{c7e79ad4-567f-412c-8738-289b2cd29c59}"}, "branch": {"name": "default"}}, "reason": "", "source": {"commit": {"hash": "cceb0492f589", "type": "commit", "links": {"self": {"href": "data/repositories/osrf/sdf_tutorials/commit/cceb0492f589.json"}, "html": {"href": "#!/osrf/sdf_tutorials/commits/cceb0492f589"}}}, "repository": {"links": {"self": {"href": "data/repositories/osrf/sdf_tutorials.json"}, "html": {"href": "#!/osrf/sdf_tutorials"}, "avatar": {"href": "data/bytebucket.org/ravatar/{c7e79ad4-567f-412c-8738-289b2cd29c59}ts=markdown"}}, "type": "repository", "name": "sdf_tutorials", "full_name": "osrf/sdf_tutorials", "uuid": "{c7e79ad4-567f-412c-8738-289b2cd29c59}"}, "branch": {"name": "pose_frame_parsing_proposal"}}, "state": "OPEN", "author": {"display_name": "Steve Peters", "uuid": "{2ccfed09-18b8-4921-8d58-15ef01092802}", "links": {"self": {"href": "https://api.bitbucket.org/2.0/users/%7B2ccfed09-18b8-4921-8d58-15ef01092802%7D"}, "html": {"href": "https://bitbucket.org/%7B2ccfed09-18b8-4921-8d58-15ef01092802%7D/"}, "avatar": {"href": "data/secure.gravatar.com/avatar/1fb4816dad9e68337d3096f750951f6cd=httpsavatar-management--avatars.us-west-2.prod.public.atl-paas.netinitialsSP-1.png"}}, "nickname": "Steven Peters", "type": "user", "account_id": "557058:5de38267-b118-494c-aa76-4fab35448816"}, "date": "2019-07-08T22:37:47.345428+00:00"}, "pull_request": {"type": "pullrequest", "id": 25, "links": {"self": {"href": "data/repositories/osrf/sdf_tutorials/pullrequests/25.json"}, "html": {"href": "#!/osrf/sdf_tutorials/pull-requests/25"}}, "title": "Parsing stages for proposed pose behavior"}}, {"comment": {"links": {"self": {"href": "data/repositories/osrf/sdf_tutorials/pullrequests/25/comments/108482849.json"}, "html": {"href": "#!/osrf/sdf_tutorials/pull-requests/25/_/diff#comment-108482849"}}, "parent": {"id": 108020945, "links": {"self": {"href": "data/repositories/osrf/sdf_tutorials/pullrequests/25/comments/108020945.json"}, "html": {"href": "#!/osrf/sdf_tutorials/pull-requests/25/_/diff#comment-108020945"}}}, "deleted": false, "pullrequest": {"type": "pullrequest", "id": 25, "links": {"self": {"href": "data/repositories/osrf/sdf_tutorials/pullrequests/25.json"}, "html": {"href": "#!/osrf/sdf_tutorials/pull-requests/25"}}, "title": "Parsing stages for proposed pose behavior"}, "content": {"raw": "this is not yet finished, I still need to add the steps for `//world/frame` and `//world/model/pose`", "markup": "markdown", "html": "<p>this is not yet finished, I still need to add the steps for <code>//world/frame</code> and <code>//world/model/pose</code></p>", "type": "rendered"}, "created_on": "2019-07-08T19:33:24.139807+00:00", "user": {"display_name": "Steve Peters", "uuid": "{2ccfed09-18b8-4921-8d58-15ef01092802}", "links": {"self": {"href": "https://api.bitbucket.org/2.0/users/%7B2ccfed09-18b8-4921-8d58-15ef01092802%7D"}, "html": {"href": "https://bitbucket.org/%7B2ccfed09-18b8-4921-8d58-15ef01092802%7D/"}, "avatar": {"href": "data/secure.gravatar.com/avatar/1fb4816dad9e68337d3096f750951f6cd=httpsavatar-management--avatars.us-west-2.prod.public.atl-paas.netinitialsSP-1.png"}}, "nickname": "Steven Peters", "type": "user", "account_id": "557058:5de38267-b118-494c-aa76-4fab35448816"}, "updated_on": "2019-07-08T19:33:24.151797+00:00", "type": "pullrequest_comment", "id": 108482849}, "pull_request": {"type": "pullrequest", "id": 25, "links": {"self": {"href": "data/repositories/osrf/sdf_tutorials/pullrequests/25.json"}, "html": {"href": "#!/osrf/sdf_tutorials/pull-requests/25"}}, "title": "Parsing stages for proposed pose behavior"}}, {"comment": {"links": {"self": {"href": "data/repositories/osrf/sdf_tutorials/pullrequests/25/comments/108482647.json"}, "html": {"href": "#!/osrf/sdf_tutorials/pull-requests/25/_/diff#comment-108482647"}}, "parent": {"id": 108481750, "links": {"self": {"href": "data/repositories/osrf/sdf_tutorials/pullrequests/25/comments/108481750.json"}, "html": {"href": "#!/osrf/sdf_tutorials/pull-requests/25/_/diff#comment-108481750"}}}, "deleted": false, "pullrequest": {"type": "pullrequest", "id": 25, "links": {"self": {"href": "data/repositories/osrf/sdf_tutorials/pullrequests/25.json"}, "html": {"href": "#!/osrf/sdf_tutorials/pull-requests/25"}}, "title": "Parsing stages for proposed pose behavior"}, "content": {"raw": "done", "markup": "markdown", "html": "<p>done</p>", "type": "rendered"}, "created_on": "2019-07-08T19:31:32.041611+00:00", "user": {"display_name": "Steve Peters", "uuid": "{2ccfed09-18b8-4921-8d58-15ef01092802}", "links": {"self": {"href": "https://api.bitbucket.org/2.0/users/%7B2ccfed09-18b8-4921-8d58-15ef01092802%7D"}, "html": {"href": "https://bitbucket.org/%7B2ccfed09-18b8-4921-8d58-15ef01092802%7D/"}, "avatar": {"href": "data/secure.gravatar.com/avatar/1fb4816dad9e68337d3096f750951f6cd=httpsavatar-management--avatars.us-west-2.prod.public.atl-paas.netinitialsSP-1.png"}}, "nickname": "Steven Peters", "type": "user", "account_id": "557058:5de38267-b118-494c-aa76-4fab35448816"}, "updated_on": "2019-07-08T19:31:32.055396+00:00", "type": "pullrequest_comment", "id": 108482647}, "pull_request": {"type": "pullrequest", "id": 25, "links": {"self": {"href": "data/repositories/osrf/sdf_tutorials/pullrequests/25.json"}, "html": {"href": "#!/osrf/sdf_tutorials/pull-requests/25"}}, "title": "Parsing stages for proposed pose behavior"}}, {"update": {"description": "The main change here is to document the parsing states for the proposed pose frame semantics, highlighting the differences with the legacy behavior using italics. I've also included two small changes in 8701b60 and b213344 that change the target version of the SDF spec to 1.7 (instead of 2.0) and also refers to some links as documentation rather than tutorials.", "title": "Parsing stages for proposed pose behavior", "destination": {"commit": {"hash": "319d63cfb4e8", "type": "commit", "links": {"self": {"href": "data/repositories/osrf/sdf_tutorials/commit/319d63cfb4e8.json"}, "html": {"href": "#!/osrf/sdf_tutorials/commits/319d63cfb4e8"}}}, "repository": {"links": {"self": {"href": "data/repositories/osrf/sdf_tutorials.json"}, "html": {"href": "#!/osrf/sdf_tutorials"}, "avatar": {"href": "data/bytebucket.org/ravatar/{c7e79ad4-567f-412c-8738-289b2cd29c59}ts=markdown"}}, "type": "repository", "name": "sdf_tutorials", "full_name": "osrf/sdf_tutorials", "uuid": "{c7e79ad4-567f-412c-8738-289b2cd29c59}"}, "branch": {"name": "default"}}, "reason": "", "source": {"commit": {"hash": "2a16f6db2387", "type": "commit", "links": {"self": {"href": "data/repositories/osrf/sdf_tutorials/commit/2a16f6db2387.json"}, "html": {"href": "#!/osrf/sdf_tutorials/commits/2a16f6db2387"}}}, "repository": {"links": {"self": {"href": "data/repositories/osrf/sdf_tutorials.json"}, "html": {"href": "#!/osrf/sdf_tutorials"}, "avatar": {"href": "data/bytebucket.org/ravatar/{c7e79ad4-567f-412c-8738-289b2cd29c59}ts=markdown"}}, "type": "repository", "name": "sdf_tutorials", "full_name": "osrf/sdf_tutorials", "uuid": "{c7e79ad4-567f-412c-8738-289b2cd29c59}"}, "branch": {"name": "pose_frame_parsing_proposal"}}, "state": "OPEN", "author": {"display_name": "Steve Peters", "uuid": "{2ccfed09-18b8-4921-8d58-15ef01092802}", "links": {"self": {"href": "https://api.bitbucket.org/2.0/users/%7B2ccfed09-18b8-4921-8d58-15ef01092802%7D"}, "html": {"href": "https://bitbucket.org/%7B2ccfed09-18b8-4921-8d58-15ef01092802%7D/"}, "avatar": {"href": "data/secure.gravatar.com/avatar/1fb4816dad9e68337d3096f750951f6cd=httpsavatar-management--avatars.us-west-2.prod.public.atl-paas.netinitialsSP-1.png"}}, "nickname": "Steven Peters", "type": "user", "account_id": "557058:5de38267-b118-494c-aa76-4fab35448816"}, "date": "2019-07-08T19:31:18.560257+00:00"}, "pull_request": {"type": "pullrequest", "id": 25, "links": {"self": {"href": "data/repositories/osrf/sdf_tutorials/pullrequests/25.json"}, "html": {"href": "#!/osrf/sdf_tutorials/pull-requests/25"}}, "title": "Parsing stages for proposed pose behavior"}}, {"update": {"description": "The main change here is to document the parsing states for the proposed pose frame semantics, highlighting the differences with the legacy behavior using italics. I've also included two small changes in 8701b60 and b213344 that change the target version of the SDF spec to 1.7 (instead of 2.0) and also refers to some links as documentation rather than tutorials.", "title": "Parsing stages for proposed pose behavior", "destination": {"commit": {"hash": "319d63cfb4e8", "type": "commit", "links": {"self": {"href": "data/repositories/osrf/sdf_tutorials/commit/319d63cfb4e8.json"}, "html": {"href": "#!/osrf/sdf_tutorials/commits/319d63cfb4e8"}}}, "repository": {"links": {"self": {"href": "data/repositories/osrf/sdf_tutorials.json"}, "html": {"href": "#!/osrf/sdf_tutorials"}, "avatar": {"href": "data/bytebucket.org/ravatar/{c7e79ad4-567f-412c-8738-289b2cd29c59}ts=markdown"}}, "type": "repository", "name": "sdf_tutorials", "full_name": "osrf/sdf_tutorials", "uuid": "{c7e79ad4-567f-412c-8738-289b2cd29c59}"}, "branch": {"name": "default"}}, "reason": "", "source": {"commit": {"hash": "8e55ab9b52ec", "type": "commit", "links": {"self": {"href": "data/repositories/osrf/sdf_tutorials/commit/8e55ab9b52ec.json"}, "html": {"href": "#!/osrf/sdf_tutorials/commits/8e55ab9b52ec"}}}, "repository": {"links": {"self": {"href": "data/repositories/osrf/sdf_tutorials.json"}, "html": {"href": "#!/osrf/sdf_tutorials"}, "avatar": {"href": "data/bytebucket.org/ravatar/{c7e79ad4-567f-412c-8738-289b2cd29c59}ts=markdown"}}, "type": "repository", "name": "sdf_tutorials", "full_name": "osrf/sdf_tutorials", "uuid": "{c7e79ad4-567f-412c-8738-289b2cd29c59}"}, "branch": {"name": "pose_frame_parsing_proposal"}}, "state": "OPEN", "author": {"display_name": "Steve Peters", "uuid": "{2ccfed09-18b8-4921-8d58-15ef01092802}", "links": {"self": {"href": "https://api.bitbucket.org/2.0/users/%7B2ccfed09-18b8-4921-8d58-15ef01092802%7D"}, "html": {"href": "https://bitbucket.org/%7B2ccfed09-18b8-4921-8d58-15ef01092802%7D/"}, "avatar": {"href": "data/secure.gravatar.com/avatar/1fb4816dad9e68337d3096f750951f6cd=httpsavatar-management--avatars.us-west-2.prod.public.atl-paas.netinitialsSP-1.png"}}, "nickname": "Steven Peters", "type": "user", "account_id": "557058:5de38267-b118-494c-aa76-4fab35448816"}, "date": "2019-07-08T19:31:08.547742+00:00"}, "pull_request": {"type": "pullrequest", "id": 25, "links": {"self": {"href": "data/repositories/osrf/sdf_tutorials/pullrequests/25.json"}, "html": {"href": "#!/osrf/sdf_tutorials/pull-requests/25"}}, "title": "Parsing stages for proposed pose behavior"}}, {"update": {"description": "The main change here is to document the parsing states for the proposed pose frame semantics, highlighting the differences with the legacy behavior using italics. I've also included two small changes in 8701b60 and b213344 that change the target version of the SDF spec to 1.7 (instead of 2.0) and also refers to some links as documentation rather than tutorials.", "title": "Parsing stages for proposed pose behavior", "destination": {"commit": {"hash": "319d63cfb4e8", "type": "commit", "links": {"self": {"href": "data/repositories/osrf/sdf_tutorials/commit/319d63cfb4e8.json"}, "html": {"href": "#!/osrf/sdf_tutorials/commits/319d63cfb4e8"}}}, "repository": {"links": {"self": {"href": "data/repositories/osrf/sdf_tutorials.json"}, "html": {"href": "#!/osrf/sdf_tutorials"}, "avatar": {"href": "data/bytebucket.org/ravatar/{c7e79ad4-567f-412c-8738-289b2cd29c59}ts=markdown"}}, "type": "repository", "name": "sdf_tutorials", "full_name": "osrf/sdf_tutorials", "uuid": "{c7e79ad4-567f-412c-8738-289b2cd29c59}"}, "branch": {"name": "default"}}, "reason": "", "source": {"commit": {"hash": "8e55ab9b52ec", "type": "commit", "links": {"self": {"href": "data/repositories/osrf/sdf_tutorials/commit/8e55ab9b52ec.json"}, "html": {"href": "#!/osrf/sdf_tutorials/commits/8e55ab9b52ec"}}}, "repository": {"links": {"self": {"href": "data/repositories/osrf/sdf_tutorials.json"}, "html": {"href": "#!/osrf/sdf_tutorials"}, "avatar": {"href": "data/bytebucket.org/ravatar/{c7e79ad4-567f-412c-8738-289b2cd29c59}ts=markdown"}}, "type": "repository", "name": "sdf_tutorials", "full_name": "osrf/sdf_tutorials", "uuid": "{c7e79ad4-567f-412c-8738-289b2cd29c59}"}, "branch": {"name": "pose_frame_parsing_proposal"}}, "state": "OPEN", "author": {"display_name": "Steve Peters", "uuid": "{2ccfed09-18b8-4921-8d58-15ef01092802}", "links": {"self": {"href": "https://api.bitbucket.org/2.0/users/%7B2ccfed09-18b8-4921-8d58-15ef01092802%7D"}, "html": {"href": "https://bitbucket.org/%7B2ccfed09-18b8-4921-8d58-15ef01092802%7D/"}, "avatar": {"href": "data/secure.gravatar.com/avatar/1fb4816dad9e68337d3096f750951f6cd=httpsavatar-management--avatars.us-west-2.prod.public.atl-paas.netinitialsSP-1.png"}}, "nickname": "Steven Peters", "type": "user", "account_id": "557058:5de38267-b118-494c-aa76-4fab35448816"}, "date": "2019-07-08T19:31:08.412921+00:00"}, "pull_request": {"type": "pullrequest", "id": 25, "links": {"self": {"href": "data/repositories/osrf/sdf_tutorials/pullrequests/25.json"}, "html": {"href": "#!/osrf/sdf_tutorials/pull-requests/25"}}, "title": "Parsing stages for proposed pose behavior"}}, {"comment": {"links": {"self": {"href": "data/repositories/osrf/sdf_tutorials/pullrequests/25/comments/108481750.json"}, "html": {"href": "#!/osrf/sdf_tutorials/pull-requests/25/_/diff#comment-108481750"}}, "deleted": false, "pullrequest": {"type": "pullrequest", "id": 25, "links": {"self": {"href": "data/repositories/osrf/sdf_tutorials/pullrequests/25.json"}, "html": {"href": "#!/osrf/sdf_tutorials/pull-requests/25"}}, "title": "Parsing stages for proposed pose behavior"}, "content": {"raw": "Given that `world_frame` merged, can you retarget / rebase this PR?", "markup": "markdown", "html": "<p>Given that <code>world_frame</code> merged, can you retarget / rebase this PR?</p>", "type": "rendered"}, "created_on": "2019-07-08T19:23:06.351653+00:00", "user": {"display_name": "Eric Cousineau", "uuid": "{71c9fc05-02c8-45e1-adfa-13c8ac3399dc}", "links": {"self": {"href": "https://api.bitbucket.org/2.0/users/%7B71c9fc05-02c8-45e1-adfa-13c8ac3399dc%7D"}, "html": {"href": "https://bitbucket.org/%7B71c9fc05-02c8-45e1-adfa-13c8ac3399dc%7D/"}, "avatar": {"href": "https://avatar-management--avatars.us-west-2.prod.public.atl-paas.net/557057:f3a199b9-5784-4964-9644-6ef224bc7dc1/28a4d748-0fd4-4038-bf3d-55a77eb73ede/128"}}, "nickname": "eacousineau", "type": "user", "account_id": "557057:f3a199b9-5784-4964-9644-6ef224bc7dc1"}, "updated_on": "2019-07-08T19:23:06.363599+00:00", "type": "pullrequest_comment", "id": 108481750}, "pull_request": {"type": "pullrequest", "id": 25, "links": {"self": {"href": "data/repositories/osrf/sdf_tutorials/pullrequests/25.json"}, "html": {"href": "#!/osrf/sdf_tutorials/pull-requests/25"}}, "title": "Parsing stages for proposed pose behavior"}}, {"update": {"description": "The main change here is to document the parsing states for the proposed pose frame semantics, highlighting the differences with the legacy behavior using italics. I've also included two small changes in 8701b60 and b213344 that change the target version of the SDF spec to 1.7 (instead of 2.0) and also refers to some links as documentation rather than tutorials.", "title": "Parsing stages for proposed pose behavior", "destination": {"commit": {"hash": "82e02005ca0f", "type": "commit", "links": {"self": {"href": "data/repositories/osrf/sdf_tutorials/commit/82e02005ca0f.json"}, "html": {"href": "#!/osrf/sdf_tutorials/commits/82e02005ca0f"}}}, "repository": {"links": {"self": {"href": "data/repositories/osrf/sdf_tutorials.json"}, "html": {"href": "#!/osrf/sdf_tutorials"}, "avatar": {"href": "data/bytebucket.org/ravatar/{c7e79ad4-567f-412c-8738-289b2cd29c59}ts=markdown"}}, "type": "repository", "name": "sdf_tutorials", "full_name": "osrf/sdf_tutorials", "uuid": "{c7e79ad4-567f-412c-8738-289b2cd29c59}"}, "branch": {"name": "default"}}, "reason": "", "source": {"commit": {"hash": "8e55ab9b52ec", "type": "commit", "links": {"self": {"href": "data/repositories/osrf/sdf_tutorials/commit/8e55ab9b52ec.json"}, "html": {"href": "#!/osrf/sdf_tutorials/commits/8e55ab9b52ec"}}}, "repository": {"links": {"self": {"href": "data/repositories/osrf/sdf_tutorials.json"}, "html": {"href": "#!/osrf/sdf_tutorials"}, "avatar": {"href": "data/bytebucket.org/ravatar/{c7e79ad4-567f-412c-8738-289b2cd29c59}ts=markdown"}}, "type": "repository", "name": "sdf_tutorials", "full_name": "osrf/sdf_tutorials", "uuid": "{c7e79ad4-567f-412c-8738-289b2cd29c59}"}, "branch": {"name": "pose_frame_parsing_proposal"}}, "state": "OPEN", "author": {"display_name": "Steve Peters", "uuid": "{2ccfed09-18b8-4921-8d58-15ef01092802}", "links": {"self": {"href": "https://api.bitbucket.org/2.0/users/%7B2ccfed09-18b8-4921-8d58-15ef01092802%7D"}, "html": {"href": "https://bitbucket.org/%7B2ccfed09-18b8-4921-8d58-15ef01092802%7D/"}, "avatar": {"href": "data/secure.gravatar.com/avatar/1fb4816dad9e68337d3096f750951f6cd=httpsavatar-management--avatars.us-west-2.prod.public.atl-paas.netinitialsSP-1.png"}}, "nickname": "Steven Peters", "type": "user", "account_id": "557058:5de38267-b118-494c-aa76-4fab35448816"}, "date": "2019-07-03T22:05:42.197202+00:00"}, "pull_request": {"type": "pullrequest", "id": 25, "links": {"self": {"href": "data/repositories/osrf/sdf_tutorials/pullrequests/25.json"}, "html": {"href": "#!/osrf/sdf_tutorials/pull-requests/25"}}, "title": "Parsing stages for proposed pose behavior"}}, {"update": {"description": "The main change here is to document the parsing states for the proposed pose frame semantics, highlighting the differences with the legacy behavior using italics. I've also included two small changes in 8701b60 and b213344 that change the target version of the SDF spec to 1.7 (instead of 2.0) and also refers to some links as documentation rather than tutorials.", "title": "Parsing stages for proposed pose behavior", "destination": {"commit": {"hash": "82e02005ca0f", "type": "commit", "links": {"self": {"href": "data/repositories/osrf/sdf_tutorials/commit/82e02005ca0f.json"}, "html": {"href": "#!/osrf/sdf_tutorials/commits/82e02005ca0f"}}}, "repository": {"links": {"self": {"href": "data/repositories/osrf/sdf_tutorials.json"}, "html": {"href": "#!/osrf/sdf_tutorials"}, "avatar": {"href": "data/bytebucket.org/ravatar/{c7e79ad4-567f-412c-8738-289b2cd29c59}ts=markdown"}}, "type": "repository", "name": "sdf_tutorials", "full_name": "osrf/sdf_tutorials", "uuid": "{c7e79ad4-567f-412c-8738-289b2cd29c59}"}, "branch": {"name": "default"}}, "reason": "", "source": {"commit": {"hash": "3d9c1393c132", "type": "commit", "links": {"self": {"href": "data/repositories/osrf/sdf_tutorials/commit/3d9c1393c132.json"}, "html": {"href": "#!/osrf/sdf_tutorials/commits/3d9c1393c132"}}}, "repository": {"links": {"self": {"href": "data/repositories/osrf/sdf_tutorials.json"}, "html": {"href": "#!/osrf/sdf_tutorials"}, "avatar": {"href": "data/bytebucket.org/ravatar/{c7e79ad4-567f-412c-8738-289b2cd29c59}ts=markdown"}}, "type": "repository", "name": "sdf_tutorials", "full_name": "osrf/sdf_tutorials", "uuid": "{c7e79ad4-567f-412c-8738-289b2cd29c59}"}, "branch": {"name": "pose_frame_parsing_proposal"}}, "state": "OPEN", "author": {"display_name": "Steve Peters", "uuid": "{2ccfed09-18b8-4921-8d58-15ef01092802}", "links": {"self": {"href": "https://api.bitbucket.org/2.0/users/%7B2ccfed09-18b8-4921-8d58-15ef01092802%7D"}, "html": {"href": "https://bitbucket.org/%7B2ccfed09-18b8-4921-8d58-15ef01092802%7D/"}, "avatar": {"href": "data/secure.gravatar.com/avatar/1fb4816dad9e68337d3096f750951f6cd=httpsavatar-management--avatars.us-west-2.prod.public.atl-paas.netinitialsSP-1.png"}}, "nickname": "Steven Peters", "type": "user", "account_id": "557058:5de38267-b118-494c-aa76-4fab35448816"}, "date": "2019-07-03T21:03:49.974151+00:00"}, "pull_request": {"type": "pullrequest", "id": 25, "links": {"self": {"href": "data/repositories/osrf/sdf_tutorials/pullrequests/25.json"}, "html": {"href": "#!/osrf/sdf_tutorials/pull-requests/25"}}, "title": "Parsing stages for proposed pose behavior"}}, {"update": {"description": "The main change here is to document the parsing states for the proposed pose frame semantics, highlighting the differences with the legacy behavior using italics. I've also included two small changes in 8701b60 and b213344 that change the target version of the SDF spec to 1.7 (instead of 2.0) and also refers to some links as documentation rather than tutorials.", "title": "Parsing stages for proposed pose behavior", "destination": {"commit": {"hash": "82e02005ca0f", "type": "commit", "links": {"self": {"href": "data/repositories/osrf/sdf_tutorials/commit/82e02005ca0f.json"}, "html": {"href": "#!/osrf/sdf_tutorials/commits/82e02005ca0f"}}}, "repository": {"links": {"self": {"href": "data/repositories/osrf/sdf_tutorials.json"}, "html": {"href": "#!/osrf/sdf_tutorials"}, "avatar": {"href": "data/bytebucket.org/ravatar/{c7e79ad4-567f-412c-8738-289b2cd29c59}ts=markdown"}}, "type": "repository", "name": "sdf_tutorials", "full_name": "osrf/sdf_tutorials", "uuid": "{c7e79ad4-567f-412c-8738-289b2cd29c59}"}, "branch": {"name": "default"}}, "reason": "", "source": {"commit": {"hash": "060ef1199e9e", "type": "commit", "links": {"self": {"href": "data/repositories/osrf/sdf_tutorials/commit/060ef1199e9e.json"}, "html": {"href": "#!/osrf/sdf_tutorials/commits/060ef1199e9e"}}}, "repository": {"links": {"self": {"href": "data/repositories/osrf/sdf_tutorials.json"}, "html": {"href": "#!/osrf/sdf_tutorials"}, "avatar": {"href": "data/bytebucket.org/ravatar/{c7e79ad4-567f-412c-8738-289b2cd29c59}ts=markdown"}}, "type": "repository", "name": "sdf_tutorials", "full_name": "osrf/sdf_tutorials", "uuid": "{c7e79ad4-567f-412c-8738-289b2cd29c59}"}, "branch": {"name": "pose_frame_parsing_proposal"}}, "state": "OPEN", "author": {"display_name": "Steve Peters", "uuid": "{2ccfed09-18b8-4921-8d58-15ef01092802}", "links": {"self": {"href": "https://api.bitbucket.org/2.0/users/%7B2ccfed09-18b8-4921-8d58-15ef01092802%7D"}, "html": {"href": "https://bitbucket.org/%7B2ccfed09-18b8-4921-8d58-15ef01092802%7D/"}, "avatar": {"href": "data/secure.gravatar.com/avatar/1fb4816dad9e68337d3096f750951f6cd=httpsavatar-management--avatars.us-west-2.prod.public.atl-paas.netinitialsSP-1.png"}}, "nickname": "Steven Peters", "type": "user", "account_id": "557058:5de38267-b118-494c-aa76-4fab35448816"}, "date": "2019-07-03T18:20:22.683112+00:00"}, "pull_request": {"type": "pullrequest", "id": 25, "links": {"self": {"href": "data/repositories/osrf/sdf_tutorials/pullrequests/25.json"}, "html": {"href": "#!/osrf/sdf_tutorials/pull-requests/25"}}, "title": "Parsing stages for proposed pose behavior"}}, {"comment": {"links": {"self": {"href": "data/repositories/osrf/sdf_tutorials/pullrequests/25/comments/108020945.json"}, "html": {"href": "#!/osrf/sdf_tutorials/pull-requests/25/_/diff#comment-108020945"}}, "deleted": false, "pullrequest": {"type": "pullrequest", "id": 25, "links": {"self": {"href": "data/repositories/osrf/sdf_tutorials/pullrequests/25.json"}, "html": {"href": "#!/osrf/sdf_tutorials/pull-requests/25"}}, "title": "Parsing stages for proposed pose behavior"}, "content": {"raw": "I've re-targeted this to the `world_frame` branch of pull request #21 and will update the parsing stages to include the `//world/frame`", "markup": "markdown", "html": "<p>I've re-targeted this to the <code>world_frame</code> branch of <a href=\"#!/osrf/sdf_tutorials/pull-requests/21/world-frame\" rel=\"nofollow\" class=\"ap-connect-link\">pull request #21</a> and will update the parsing stages to include the <code>//world/frame</code></p>", "type": "rendered"}, "created_on": "2019-07-03T18:18:38.737649+00:00", "user": {"display_name": "Steve Peters", "uuid": "{2ccfed09-18b8-4921-8d58-15ef01092802}", "links": {"self": {"href": "https://api.bitbucket.org/2.0/users/%7B2ccfed09-18b8-4921-8d58-15ef01092802%7D"}, "html": {"href": "https://bitbucket.org/%7B2ccfed09-18b8-4921-8d58-15ef01092802%7D/"}, "avatar": {"href": "data/secure.gravatar.com/avatar/1fb4816dad9e68337d3096f750951f6cd=httpsavatar-management--avatars.us-west-2.prod.public.atl-paas.netinitialsSP-1.png"}}, "nickname": "Steven Peters", "type": "user", "account_id": "557058:5de38267-b118-494c-aa76-4fab35448816"}, "updated_on": "2019-07-03T18:18:38.748070+00:00", "type": "pullrequest_comment", "id": 108020945}, "pull_request": {"type": "pullrequest", "id": 25, "links": {"self": {"href": "data/repositories/osrf/sdf_tutorials/pullrequests/25.json"}, "html": {"href": "#!/osrf/sdf_tutorials/pull-requests/25"}}, "title": "Parsing stages for proposed pose behavior"}}, {"update": {"description": "The main change here is to document the parsing states for the proposed pose frame semantics, highlighting the differences with the legacy behavior using italics. I've also included two small changes in 8701b60 and b213344 that change the target version of the SDF spec to 1.7 (instead of 2.0) and also refers to some links as documentation rather than tutorials.", "title": "Parsing stages for proposed pose behavior", "destination": {"commit": {"hash": "9a6ba6432c7a", "type": "commit", "links": {"self": {"href": "data/repositories/osrf/sdf_tutorials/commit/9a6ba6432c7a.json"}, "html": {"href": "#!/osrf/sdf_tutorials/commits/9a6ba6432c7a"}}}, "repository": {"links": {"self": {"href": "data/repositories/osrf/sdf_tutorials.json"}, "html": {"href": "#!/osrf/sdf_tutorials"}, "avatar": {"href": "data/bytebucket.org/ravatar/{c7e79ad4-567f-412c-8738-289b2cd29c59}ts=markdown"}}, "type": "repository", "name": "sdf_tutorials", "full_name": "osrf/sdf_tutorials", "uuid": "{c7e79ad4-567f-412c-8738-289b2cd29c59}"}, "branch": {"name": "default"}}, "reason": "", "source": {"commit": {"hash": "2fd0b7529013", "type": "commit", "links": {"self": {"href": "data/repositories/osrf/sdf_tutorials/commit/2fd0b7529013.json"}, "html": {"href": "#!/osrf/sdf_tutorials/commits/2fd0b7529013"}}}, "repository": {"links": {"self": {"href": "data/repositories/osrf/sdf_tutorials.json"}, "html": {"href": "#!/osrf/sdf_tutorials"}, "avatar": {"href": "data/bytebucket.org/ravatar/{c7e79ad4-567f-412c-8738-289b2cd29c59}ts=markdown"}}, "type": "repository", "name": "sdf_tutorials", "full_name": "osrf/sdf_tutorials", "uuid": "{c7e79ad4-567f-412c-8738-289b2cd29c59}"}, "branch": {"name": "pose_frame_parsing_proposal"}}, "state": "OPEN", "author": {"display_name": "Steve Peters", "uuid": "{2ccfed09-18b8-4921-8d58-15ef01092802}", "links": {"self": {"href": "https://api.bitbucket.org/2.0/users/%7B2ccfed09-18b8-4921-8d58-15ef01092802%7D"}, "html": {"href": "https://bitbucket.org/%7B2ccfed09-18b8-4921-8d58-15ef01092802%7D/"}, "avatar": {"href": "data/secure.gravatar.com/avatar/1fb4816dad9e68337d3096f750951f6cd=httpsavatar-management--avatars.us-west-2.prod.public.atl-paas.netinitialsSP-1.png"}}, "nickname": "Steven Peters", "type": "user", "account_id": "557058:5de38267-b118-494c-aa76-4fab35448816"}, "date": "2019-07-03T18:17:54.493632+00:00"}, "pull_request": {"type": "pullrequest", "id": 25, "links": {"self": {"href": "data/repositories/osrf/sdf_tutorials/pullrequests/25.json"}, "html": {"href": "#!/osrf/sdf_tutorials/pull-requests/25"}}, "title": "Parsing stages for proposed pose behavior"}}, {"update": {"description": "The main change here is to document the parsing states for the proposed pose frame semantics, highlighting the differences with the legacy behavior using italics. I've also included two small changes in 8701b60 and b213344 that change the target version of the SDF spec to 1.7 (instead of 2.0) and also refers to some links as documentation rather than tutorials.", "title": "Parsing stages for proposed pose behavior", "destination": {"commit": {"hash": "9a6ba6432c7a", "type": "commit", "links": {"self": {"href": "data/repositories/osrf/sdf_tutorials/commit/9a6ba6432c7a.json"}, "html": {"href": "#!/osrf/sdf_tutorials/commits/9a6ba6432c7a"}}}, "repository": {"links": {"self": {"href": "data/repositories/osrf/sdf_tutorials.json"}, "html": {"href": "#!/osrf/sdf_tutorials"}, "avatar": {"href": "data/bytebucket.org/ravatar/{c7e79ad4-567f-412c-8738-289b2cd29c59}ts=markdown"}}, "type": "repository", "name": "sdf_tutorials", "full_name": "osrf/sdf_tutorials", "uuid": "{c7e79ad4-567f-412c-8738-289b2cd29c59}"}, "branch": {"name": "default"}}, "reason": "", "source": {"commit": {"hash": "2fd0b7529013", "type": "commit", "links": {"self": {"href": "data/repositories/osrf/sdf_tutorials/commit/2fd0b7529013.json"}, "html": {"href": "#!/osrf/sdf_tutorials/commits/2fd0b7529013"}}}, "repository": {"links": {"self": {"href": "data/repositories/osrf/sdf_tutorials.json"}, "html": {"href": "#!/osrf/sdf_tutorials"}, "avatar": {"href": "data/bytebucket.org/ravatar/{c7e79ad4-567f-412c-8738-289b2cd29c59}ts=markdown"}}, "type": "repository", "name": "sdf_tutorials", "full_name": "osrf/sdf_tutorials", "uuid": "{c7e79ad4-567f-412c-8738-289b2cd29c59}"}, "branch": {"name": "pose_frame_parsing_proposal"}}, "state": "OPEN", "author": {"display_name": "Steve Peters", "uuid": "{2ccfed09-18b8-4921-8d58-15ef01092802}", "links": {"self": {"href": "https://api.bitbucket.org/2.0/users/%7B2ccfed09-18b8-4921-8d58-15ef01092802%7D"}, "html": {"href": "https://bitbucket.org/%7B2ccfed09-18b8-4921-8d58-15ef01092802%7D/"}, "avatar": {"href": "data/secure.gravatar.com/avatar/1fb4816dad9e68337d3096f750951f6cd=httpsavatar-management--avatars.us-west-2.prod.public.atl-paas.netinitialsSP-1.png"}}, "nickname": "Steven Peters", "type": "user", "account_id": "557058:5de38267-b118-494c-aa76-4fab35448816"}, "date": "2019-07-03T18:17:54.439247+00:00"}, "pull_request": {"type": "pullrequest", "id": 25, "links": {"self": {"href": "data/repositories/osrf/sdf_tutorials/pullrequests/25.json"}, "html": {"href": "#!/osrf/sdf_tutorials/pull-requests/25"}}, "title": "Parsing stages for proposed pose behavior"}}, {"update": {"description": "The main change here is to document the parsing states for the proposed pose frame semantics, highlighting the differences with the legacy behavior using italics. I've also included two small changes in 8701b60 and b213344 that change the target version of the SDF spec to 1.7 (instead of 2.0) and also refers to some links as documentation rather than tutorials.", "title": "Parsing stages for proposed pose behavior", "destination": {"commit": {"hash": "6acad104b588", "type": "commit", "links": {"self": {"href": "data/repositories/osrf/sdf_tutorials/commit/6acad104b588.json"}, "html": {"href": "#!/osrf/sdf_tutorials/commits/6acad104b588"}}}, "repository": {"links": {"self": {"href": "data/repositories/osrf/sdf_tutorials.json"}, "html": {"href": "#!/osrf/sdf_tutorials"}, "avatar": {"href": "data/bytebucket.org/ravatar/{c7e79ad4-567f-412c-8738-289b2cd29c59}ts=markdown"}}, "type": "repository", "name": "sdf_tutorials", "full_name": "osrf/sdf_tutorials", "uuid": "{c7e79ad4-567f-412c-8738-289b2cd29c59}"}, "branch": {"name": "default"}}, "reason": "", "source": {"commit": {"hash": "2fd0b7529013", "type": "commit", "links": {"self": {"href": "data/repositories/osrf/sdf_tutorials/commit/2fd0b7529013.json"}, "html": {"href": "#!/osrf/sdf_tutorials/commits/2fd0b7529013"}}}, "repository": {"links": {"self": {"href": "data/repositories/osrf/sdf_tutorials.json"}, "html": {"href": "#!/osrf/sdf_tutorials"}, "avatar": {"href": "data/bytebucket.org/ravatar/{c7e79ad4-567f-412c-8738-289b2cd29c59}ts=markdown"}}, "type": "repository", "name": "sdf_tutorials", "full_name": "osrf/sdf_tutorials", "uuid": "{c7e79ad4-567f-412c-8738-289b2cd29c59}"}, "branch": {"name": "pose_frame_parsing_proposal"}}, "state": "OPEN", "author": {"display_name": "Steve Peters", "uuid": "{2ccfed09-18b8-4921-8d58-15ef01092802}", "links": {"self": {"href": "https://api.bitbucket.org/2.0/users/%7B2ccfed09-18b8-4921-8d58-15ef01092802%7D"}, "html": {"href": "https://bitbucket.org/%7B2ccfed09-18b8-4921-8d58-15ef01092802%7D/"}, "avatar": {"href": "data/secure.gravatar.com/avatar/1fb4816dad9e68337d3096f750951f6cd=httpsavatar-management--avatars.us-west-2.prod.public.atl-paas.netinitialsSP-1.png"}}, "nickname": "Steven Peters", "type": "user", "account_id": "557058:5de38267-b118-494c-aa76-4fab35448816"}, "date": "2019-06-26T02:44:11.746611+00:00"}, "pull_request": {"type": "pullrequest", "id": 25, "links": {"self": {"href": "data/repositories/osrf/sdf_tutorials/pullrequests/25.json"}, "html": {"href": "#!/osrf/sdf_tutorials/pull-requests/25"}}, "title": "Parsing stages for proposed pose behavior"}}, {"comment": {"links": {"self": {"href": "data/repositories/osrf/sdf_tutorials/pullrequests/25/comments/107028050.json"}, "html": {"href": "#!/osrf/sdf_tutorials/pull-requests/25/_/diff#comment-107028050"}}, "deleted": false, "pullrequest": {"type": "pullrequest", "id": 25, "links": {"self": {"href": "data/repositories/osrf/sdf_tutorials/pullrequests/25.json"}, "html": {"href": "#!/osrf/sdf_tutorials/pull-requests/25"}}, "title": "Parsing stages for proposed pose behavior"}, "content": {"raw": "preview: http://sdformat.org/tutorials?tut=pose_frame_semantics_proposal&cat=pose_semantics_docs&branch=pose_frame_parsing_proposal", "markup": "markdown", "html": "<p>preview: <a href=\"http://sdformat.org/tutorials?tut=pose_frame_semantics_proposal&amp;cat=pose_semantics_docs&amp;branch=pose_frame_parsing_proposal\" rel=\"nofollow\" class=\"ap-connect-link\">http://sdformat.org/tutorials?tut=pose_frame_semantics_proposal&amp;cat=pose_semantics_docs&amp;branch=pose_frame_parsing_proposal</a></p>", "type": "rendered"}, "created_on": "2019-06-25T19:39:25.034849+00:00", "user": {"display_name": "Steve Peters", "uuid": "{2ccfed09-18b8-4921-8d58-15ef01092802}", "links": {"self": {"href": "https://api.bitbucket.org/2.0/users/%7B2ccfed09-18b8-4921-8d58-15ef01092802%7D"}, "html": {"href": "https://bitbucket.org/%7B2ccfed09-18b8-4921-8d58-15ef01092802%7D/"}, "avatar": {"href": "data/secure.gravatar.com/avatar/1fb4816dad9e68337d3096f750951f6cd=httpsavatar-management--avatars.us-west-2.prod.public.atl-paas.netinitialsSP-1.png"}}, "nickname": "Steven Peters", "type": "user", "account_id": "557058:5de38267-b118-494c-aa76-4fab35448816"}, "updated_on": "2019-06-25T19:39:25.042884+00:00", "type": "pullrequest_comment", "id": 107028050}, "pull_request": {"type": "pullrequest", "id": 25, "links": {"self": {"href": "data/repositories/osrf/sdf_tutorials/pullrequests/25.json"}, "html": {"href": "#!/osrf/sdf_tutorials/pull-requests/25"}}, "title": "Parsing stages for proposed pose behavior"}}, {"update": {"description": "The main change here is to document the parsing states for the proposed pose frame semantics, highlighting the differences with the legacy behavior using italics. I've also included two small changes in 8701b60 and b213344 that change the target version of the SDF spec to 1.7 (instead of 2.0) and also refers to some links as documentation rather than tutorials.", "title": "Parsing stages for proposed pose behavior", "destination": {"commit": {"hash": "6acad104b588", "type": "commit", "links": {"self": {"href": "data/repositories/osrf/sdf_tutorials/commit/6acad104b588.json"}, "html": {"href": "#!/osrf/sdf_tutorials/commits/6acad104b588"}}}, "repository": {"links": {"self": {"href": "data/repositories/osrf/sdf_tutorials.json"}, "html": {"href": "#!/osrf/sdf_tutorials"}, "avatar": {"href": "data/bytebucket.org/ravatar/{c7e79ad4-567f-412c-8738-289b2cd29c59}ts=markdown"}}, "type": "repository", "name": "sdf_tutorials", "full_name": "osrf/sdf_tutorials", "uuid": "{c7e79ad4-567f-412c-8738-289b2cd29c59}"}, "branch": {"name": "default"}}, "reason": "", "source": {"commit": {"hash": "6da71ea3ff99", "type": "commit", "links": {"self": {"href": "data/repositories/osrf/sdf_tutorials/commit/6da71ea3ff99.json"}, "html": {"href": "#!/osrf/sdf_tutorials/commits/6da71ea3ff99"}}}, "repository": {"links": {"self": {"href": "data/repositories/osrf/sdf_tutorials.json"}, "html": {"href": "#!/osrf/sdf_tutorials"}, "avatar": {"href": "data/bytebucket.org/ravatar/{c7e79ad4-567f-412c-8738-289b2cd29c59}ts=markdown"}}, "type": "repository", "name": "sdf_tutorials", "full_name": "osrf/sdf_tutorials", "uuid": "{c7e79ad4-567f-412c-8738-289b2cd29c59}"}, "branch": {"name": "pose_frame_parsing_proposal"}}, "state": "OPEN", "author": {"display_name": "Steve Peters", "uuid": "{2ccfed09-18b8-4921-8d58-15ef01092802}", "links": {"self": {"href": "https://api.bitbucket.org/2.0/users/%7B2ccfed09-18b8-4921-8d58-15ef01092802%7D"}, "html": {"href": "https://bitbucket.org/%7B2ccfed09-18b8-4921-8d58-15ef01092802%7D/"}, "avatar": {"href": "data/secure.gravatar.com/avatar/1fb4816dad9e68337d3096f750951f6cd=httpsavatar-management--avatars.us-west-2.prod.public.atl-paas.netinitialsSP-1.png"}}, "nickname": "Steven Peters", "type": "user", "account_id": "557058:5de38267-b118-494c-aa76-4fab35448816"}, "date": "2019-06-25T19:38:59.631401+00:00"}, "pull_request": {"type": "pullrequest", "id": 25, "links": {"self": {"href": "data/repositories/osrf/sdf_tutorials/pullrequests/25.json"}, "html": {"href": "#!/osrf/sdf_tutorials/pull-requests/25"}}, "title": "Parsing stages for proposed pose behavior"}}, {"update": {"description": "The main change here is to document the parsing states for the proposed pose frame semantics, highlighting the differences with the legacy behavior using italics. I've also included two small changes in 8701b60 and b213344 that change the target version of the SDF spec to 1.7 (instead of 2.0) and also refers to some links as documentation rather than tutorials.", "title": "Parsing stages for proposed pose behavior", "destination": {"commit": {"hash": "6acad104b588", "type": "commit", "links": {"self": {"href": "data/repositories/osrf/sdf_tutorials/commit/6acad104b588.json"}, "html": {"href": "#!/osrf/sdf_tutorials/commits/6acad104b588"}}}, "repository": {"links": {"self": {"href": "data/repositories/osrf/sdf_tutorials.json"}, "html": {"href": "#!/osrf/sdf_tutorials"}, "avatar": {"href": "data/bytebucket.org/ravatar/{c7e79ad4-567f-412c-8738-289b2cd29c59}ts=markdown"}}, "type": "repository", "name": "sdf_tutorials", "full_name": "osrf/sdf_tutorials", "uuid": "{c7e79ad4-567f-412c-8738-289b2cd29c59}"}, "branch": {"name": "default"}}, "reason": "", "source": {"commit": {"hash": "6da71ea3ff99", "type": "commit", "links": {"self": {"href": "data/repositories/osrf/sdf_tutorials/commit/6da71ea3ff99.json"}, "html": {"href": "#!/osrf/sdf_tutorials/commits/6da71ea3ff99"}}}, "repository": {"links": {"self": {"href": "data/repositories/osrf/sdf_tutorials.json"}, "html": {"href": "#!/osrf/sdf_tutorials"}, "avatar": {"href": "data/bytebucket.org/ravatar/{c7e79ad4-567f-412c-8738-289b2cd29c59}ts=markdown"}}, "type": "repository", "name": "sdf_tutorials", "full_name": "osrf/sdf_tutorials", "uuid": "{c7e79ad4-567f-412c-8738-289b2cd29c59}"}, "branch": {"name": "pose_frame_parsing_proposal"}}, "state": "OPEN", "author": {"display_name": "Steve Peters", "uuid": "{2ccfed09-18b8-4921-8d58-15ef01092802}", "links": {"self": {"href": "https://api.bitbucket.org/2.0/users/%7B2ccfed09-18b8-4921-8d58-15ef01092802%7D"}, "html": {"href": "https://bitbucket.org/%7B2ccfed09-18b8-4921-8d58-15ef01092802%7D/"}, "avatar": {"href": "data/secure.gravatar.com/avatar/1fb4816dad9e68337d3096f750951f6cd=httpsavatar-management--avatars.us-west-2.prod.public.atl-paas.netinitialsSP-1.png"}}, "nickname": "Steven Peters", "type": "user", "account_id": "557058:5de38267-b118-494c-aa76-4fab35448816"}, "date": "2019-06-25T19:38:59.565060+00:00"}, "pull_request": {"type": "pullrequest", "id": 25, "links": {"self": {"href": "data/repositories/osrf/sdf_tutorials/pullrequests/25.json"}, "html": {"href": "#!/osrf/sdf_tutorials/pull-requests/25"}}, "title": "Parsing stages for proposed pose behavior"}}]}