{"links": {"self": {"href": "data/repositories/osrf/sdf_tutorials/pullrequests/13/comments/99874407.json"}, "html": {"href": "#!/osrf/sdf_tutorials/pull-requests/13/_/diff#comment-99874407"}}, "deleted": false, "pullrequest": {"type": "pullrequest", "id": 13, "links": {"self": {"href": "data/repositories/osrf/sdf_tutorials/pullrequests/13.json"}, "html": {"href": "#!/osrf/sdf_tutorials/pull-requests/13"}}, "title": "Replace joint frame references with Jc and Jp"}, "content": {"raw": "Agh\u2026 I have such a hard time with comments in bitbucket!\n\nok, enough of me complaining. Look at what I found in my laptop!: [https://gist.github.com/amcastro-tri/bc9aabb90a44e21e60773527b06fdea5](https://gist.github.com/amcastro-tri/bc9aabb90a44e21e60773527b06fdea5)  \n  \n I had put this together some time  in the past precisely to explain frames in Drake, but it still din\u2019t make it in a PR. If you like it, please use it in this PR!", "markup": "markdown", "html": "<p>Agh\u2026 I have such a hard time with comments in bitbucket!</p>\n<p>ok, enough of me complaining. Look at what I found in my laptop!: <a data-is-external-link=\"true\" href=\"https://gist.github.com/amcastro-tri/bc9aabb90a44e21e60773527b06fdea5\" rel=\"nofollow\">https://gist.github.com/amcastro-tri/bc9aabb90a44e21e60773527b06fdea5</a>  </p>\n<p>I had put this together some time  in the past precisely to explain frames in Drake, but it still din\u2019t make it in a PR. If you like it, please use it in this PR!</p>", "type": "rendered"}, "created_on": "2019-04-24T16:50:15.697197+00:00", "user": {"display_name": "Alejandro Castro", "uuid": "{f78f4af9-eed7-49c4-b222-5b3dc10d5093}", "links": {"self": {"href": "https://api.bitbucket.org/2.0/users/%7Bf78f4af9-eed7-49c4-b222-5b3dc10d5093%7D"}, "html": {"href": "https://bitbucket.org/%7Bf78f4af9-eed7-49c4-b222-5b3dc10d5093%7D/"}, "avatar": {"href": "data/secure.gravatar.com/avatar/9958cefe61157cc05fbc6d1a77d68a2fd=httpsavatar-management--avatars.us-west-2.prod.public.atl-paas.netinitialsAC-3.png"}}, "nickname": "amcastro0622", "type": "user", "account_id": "557058:82e5965f-3de7-463a-8d2f-5eb310e3ca12"}, "updated_on": "2019-04-24T16:50:15.772546+00:00", "type": "pullrequest_comment", "id": 99874407}